Workbook

Sheet Plano_Contas
B1: Código | C1: Conta | D1: Tipo
B2: 1.1 | C2: Ativo | D2: Ativo Circulante
B3: 1.1.01 | C3: Caixa/Banco | D3: Ativo Circulante
B4: 1.1.02 | C4: Honorários a Receber | D4: Ativo Circulante
B5: 1.2.01 | C5: Imóveis (Sede Própria) | D5: Ativo Não Circulante
B6: 1.2.02 | C6: Móveis e Utensílios | D6: Ativo Não Circulante
B7: 1.2.03 | C7: Computadores e Periféricos | D7: Ativo Não Circulante
B8: 1.2.03 | C8: (-)Depreciação Acumulada | D8: Conta Redutora do Ativo | E8: obs. Imóveis, Móveis, Computadores e Equipamentos
B9: 2.1 | C9: Passivo | D9: Passivo Circulante
B10: 2.1.01 | C10: Fornecedores | D10: Passivo Circulante | E10: obs. Parcelamentos
B11: 2.1.02 | C11: Contas a Pagar | D11: Passivo Circulante
B12: 2.1.03 | C12: Salários a Pagar | D12: Passivo Circulante
B13: 2.1.04 | C13: VT a pagar | D13: Passivo Circulante
B14: 2.1.05 | C14: 13º Sal. a pagar | D14: Passivo Circulante
B15: 2.1.06 | C15: Férias a pagar | D15: Passivo Circulante
B16: 2.1.07 | C16: FGTS a Recolher | D16: Passivo Circulante
B17: 2.1.08 | C17: INSS a Recolher | D17: Passivo Circulante | E17: obs. Sócios e Funcionários)
B18: 2.1.09 | C18: ProLabore a Pagar | D18: Passivo Circulante
B19: 2.1.10 | C19: IPTU a Pagar | D19: Passivo Circulante
B20: 2.1.11 | C20: Imposto Simples Nacional (DAS) | D20: Passivo Circulante
B21: 2.1.12 | C21: Provisões a Pagar | D21: Passivo Circulante
B22: 2.3.01 | C22: Capital Social Integralizado | D22: Patrrimônio Líquido
B23: 2.3.02 | C23: Lucros ou Prejuízos Acumulados | D23: Patrrimônio Líquido
B24: 3.1 | C24: Receita de Serviços Contábeis | D24: Receita
B25: 3.1.01 | C25: Honorários SN (ME/Comércio/Serviço) | D25: Receita
B26: 3.1.02 | C26: Honorários MEI | D26: Receita
B27: 3.1.03 | C27: Receita com Consultoria Tributária | D27: Receita
B28: 3.1.04 | C28: Receita com DIRPF (Simplificada) | D28: Receita
B29: 3.1.05 | C29: Receita com DIRPF (Completa/Complexa) | D29: Receita
... B65: 5.2.1 | C65: Imposto Simples Nacional (DAS) | D65: Resultado

Sheet Livro_Diario
A1: Data | B1: Histórico | C1: Conta Débito | D1: Conta Crédito | E1: Valor
A2: 45663 | B2: Integralização do Capital pelos sócios | C2: Caixa/Banco | D2: Capital Social Integralizado | E2: 70000
A3: 45663 | B3: PagamentoTaxa JUCESP | C3: Desp. Taxas e Registros (JUCESP/Alvará/CRC) | D3: Caixa/Banco | E3: 243.56
A4: 45663 | B4: Pagamento Licença CLBC | C4: Desp. Taxas e Registros (JUCESP/Alvará/CRC) | D4: Caixa/Banco | E4: 358
A5: 45663 | B5: Aquisição de Extintores | C5: Despesa com Equipamento de Segurança | D5: Caixa/Banco | E5: 288
A6: 45663 | B6: Pagamento taxa municipal Alvará - anual | C6: Desp. Taxas e Registros (JUCESP/Alvará/CRC) | D6: Caixa/Banco | E6: 128.56
A7: 45664 | B7: Compra mensal | C7: Despesa Limpeza e Copa | D7: Caixa/Banco | E7: 120
A8: 45664 | B8: Combustível do sócio | C8: Despesas com Veículos (Combustível) | D8: Caixa/Banco | E8: 250
A9: 45665 | B9: canetas, toner, sulfite... | C9: Despesa Material de Escritório | D9: Caixa/Banco | E9: 212
A10: 45666 | B10: Equip. de Informática | C10: Computadores e Periféricos | D10: Contas a Pagar | E10: 8298
A11: 45666 | B11: Equip. de Informática - 01/15 | C11: Contas a Pagar | D11: Caixa/Banco | E11: 553.2
A12: 45666 | B12: func. Adm. 09/01 - VT | C12: Despesa c/ VT | D12: Caixa/Banco | E12: 91
A13: 45666 | B13: VR func. Adm. 09/01 | C13: Despesa c/ VR | D13: Caixa/Banco | E13: 150
... A59: 45693 | B59: pgto folha | C59: Salários a Pagar | D59: Caixa/Banco | E59: 1360.44
A60: 45694 | B60: Consultoria MEI | C60: Caixa/Banco | D60: Receita com Consultoria Tributária | E60: 150 | G60: 56 geral
A61: 45695 | B61: compra café, descart., prod. Limpeza | C61: Despesa Limpeza e Copa | D61: Caixa/Banco | E61: 122.51
A62: 45695 | B62: Combustível | C62: Despesas com Veículos (Combustível) | D62: Caixa/Banco | E62: 300
A63: 45695 | B63: DECORE | C63: Caixa/Banco | D63: Outros Serviços (DECORE / Abertura / DASN) | E63: 380
A64: 45698 | B64: MEI (Comércio/Serviço) | C64: Caixa/Banco | D64: Honorários MEI | E64: 250
A65: 45698 | B65: MEI (Comércio/Serviço)(2) | C65: Caixa/Banco | D65: Honorários MEI | E65: 500
A66: 45693 | B66: Equipamentos de Informática - 02/15 | C66: Contas a Pagar | D66: Caixa/Banco | E66: 553.2
A67: 45698 | B67: Móveis - 02/18 | C67: Contas a Pagar | D67: Caixa/Banco | E67: 403.33
A68: 45699 | B68: Internet Vivo | C68: Despesa com Telefone e Internet | D68: Caixa/Banco | E68: 139.98
A69: 45699 | B69: DIRPF (Completa/Complexa) | C69: Caixa/Banco | D69: Receita com DIRPF (Completa/Complexa) | E69: 550
A70: 45701 | B70: DIRPF (Simplificada) (2) | C70: Caixa/Banco | D70: Receita com DIRPF (Simplificada) | E70: 300
A71: 45701 | B71: Consultoria MEI | C71: Caixa/Banco | D71: Receita com Consultoria Tributária | E71: 150
A72: 45702 | B72: Simples Nacional (ME - Serv) | C72: Caixa/Banco | D72: Honorários SN (ME/Comércio/Serviço) | E72: 800
... A94: 45716 | B94: FGTS | C94: Despesa c/ FGTS | D94: FGTS a Recolher | E94: 56
A95: 45716 | B95: INSS a recolher | C95: Salários a Pagar | D95: INSS a Recolher | E95: 226.09 | F95: =52.5+173.59 -> 226.09
A96: 45716 | B96: INSS a rcolher sócio2 | C96: ProLabore a Pagar | D96: INSS a Recolher | E96: 110
A97: 45716 | B97: Vale Transporte | C97: Salários a Pagar | D97: VT a pagar | E97: 172.91 | F97: =130.91+42 -> 172.91
A98: 45716 | B98: custos com sócios | C98: Custo c/ ProLabore | D98: ProLabore a Pagar | E98: 3000
A99: 45716 | B99: INSS dos sócios | C99: ProLabore a Pagar | D99: INSS a Recolher | E99: 330
A100: 45716 | B100: Provisão 13º Salário | C100: Despesa c/ 13º Sal. | D100: 13º Sal. A pagar | E100: 58.33
A101: 45716 | B101: Provisão Férias + 1/3 | C101: Despesa c/ Férias | D101: Férias a pagar | E101: 77.77
A102: 45716 | B102: FGTS sobre Provisões | C102: Despesa c/ FGTS | D102: FGTS a Recolher | E102: 10.88
A103: 45716 | B103: Salários | C103: Custo c/ Salários | D103: Salários a Pagar | E103: 2181.82
A104: 45716 | B104: FGTS | C104: Custo c/ FGTS | D104: FGTS a Recolher | E104: 174.55
A105: 45716 | B105: 13º - Provisão ref. Custo 01/2025 | C105: Custo c/ 13º Prov. | D105: 13º Sal. a pagar | E105: 181.82
A106: 45716 | B106: Férias - Provisão ref. Custo 01/2025 | C106: Custo c/ Férias Prov. | D106: Férias a pagar | E106: 242.42
A107: 45716 | B107: FGTS - Provisão ref. custo 01/2025 | C107: Custo c/ FGTS sobre Prov. | D107: FGTS a Recolher | E107: 33.94
A108: 45716 | B108: depreciação mensal dos imobilizado | C108: Despesa c/ Depreciação | D108: (-)Depreciação Acumulada | E108: 198.8
A109: 45719 | B109: pgto VT | C109: Despesa c/ VT | D109: Caixa/Banco | E109: 325
... A154: 45747 | B154: INSS dos sócios | C154: ProLabore a Pagar | D154: INSS a Recolher | E154: 330
A155: 45747 | B155: Provisão 13º Salário | C155: Despesa c/ 13º Sal. | D155: 13º Sal. A pagar | E155: 58.33 | H155: 56 | I155: 62 | J155: =I155-H155 -> 6 | K155: geral
A156: 45747 | B156: Provisão Férias + 1/3 | C156: Despesa c/ Férias | D156: Férias a pagar | E156: 77.77 | H156: 17 | I156: 19 | J156: =I156-H156 -> 2 | K156: fixo
A157: 45747 | B157: FGTS sobre Provisões | C157: Despesa c/ FGTS | D157: FGTS a Recolher | E157: 10.88 | H157: =H155+H156 -> 73 | I157: =I155+I156 -> 81 | J157: =I157-H157 -> 8 | K157: 0.1 | M157: 18 | N157: 0.1 | O157: 1º Semestre + 10%
A158: 45747 | B158: Salários | C158: Custo c/ Salários | D158: Salários a Pagar | E158: 2181.82
A159: 45747 | B159: FGTS | C159: Custo c/ FGTS | D159: FGTS a Recolher | E159: 174.55 | I159: 65 | J159: =I159-H155 -> 9
A160: 45747 | B160: 13º - Provisão ref. Custo 01/2025 | C160: Custo c/ 13º Prov. | D160: 13º Sal. a pagar | E160: 181.82 | I160: 20 | J160: =I160-H156 -> 3
A161: 45747 | B161: Férias - Provisão ref. Custo 01/2025 | C161: Custo c/ Férias Prov. | D161: Férias a pagar | E161: 242.42 | I161: =I159+I160 -> 85 | J161: =J159+J160 -> 12 | K161: 0.15 | M161: 25 | N161: 0.15 | O161: 1º Semestre + 15%
A162: 45747 | B162: FGTS - Provisão ref. custo 01/2025 | C162: Custo c/ FGTS sobre Prov. | D162: FGTS a Recolher | E162: 33.94
A163: 45747 | B163: Marketing | C163: Despesa com Publicidade/Redes Sociais | D163: Caixa/Banco | E163: 2200
A164: 45747 | B164: depreciação mensal dos imobilizado | C164: Despesa c/ Depreciação | D164: (-)Depreciação Acumulada | E164: 198.8

Sheet Balancete
B2: Balancete de Verificação - 1º Trimestre/2025
B3: Grupo | C3: Conta | D3: Débito | E3: Crédito | F3: Resultado | G3: Débito | H3: Crédito
B4: A | C4: Caixa/Banco | D4: =SUMIFS(Livro_Diario!$E$2:$E$301,Livro_Diario!$C$2:$C$301,Balancete!$C4) -> 98120 | E4: =SUMIFS(Livro_Diario!$E$2:$E$301,Livro_Diario!$D$2:$D$301,Balancete!$C4) -> 27925.63 | F4: =D4-E4 -> 70194.37 | G4: =ABS(IF(F4>0,F4,0)) -> 70194.37 | H4: =ABS(IF(F4>0,0,F4)) -> 0
B5: A | C5: Honorários a Receber | D5: =SUMIFS(Livro_Diario!$E$2:$E$301,Livro_Diario!$C$2:$C$301,Balancete!$C5) -> 0 | E5: =SUMIFS(Livro_Diario!$E$2:$E$301,Livro_Diario!$D$2:$D$301,Balancete!$C5) -> 0 | F5: =D5-E5 -> 0 | G5: =ABS(IF(F5>0,F5,0)) -> 0 | H5: =ABS(IF(F5>0,0,F5)) -> 0
B6: ANC | C6: Imóveis (Sede Própria) | D6: =SUMIFS(Livro_Diario!$E$2:$E$301,Livro_Diario!$C$2:$C$301,Balancete!$C6) -> 0 | E6: =SUMIFS(Livro_Diario!$E$2:$E$301,Livro_Diario!$D$2:$D$301,Balancete!$C6) -> 0 | F6: =D6-E6 -> 0 | G6: =ABS(IF(F6>0,F6,0)) -> 0 | H6: =ABS(IF(F6>0,0,F6)) -> 0
B7: ANC | C7: Móveis e Utensílios | D7: =SUMIFS(Livro_Diario!$E$2:$E$301,Livro_Diario!$C$2:$C$301,Balancete!$C7) -> 7260 | E7: =SUMIFS(Livro_Diario!$E$2:$E$301,Livro_Diario!$D$2:$D$301,Balancete!$C7) -> 0 | F7: =D7-E7 -> 7260 | G7: =ABS(IF(F7>0,F7,0)) -> 7260 | H7: =ABS(IF(F7>0,0,F7)) -> 0
B8: ANC | C8: Computadores e Periféricos | D8: =SUMIFS(Livro_Diario!$E$2:$E$301,Livro_Diario!$C$2:$C$301,Balancete!$C8) -> 8298 | E8: =SUMIFS(Livro_Diario!$E$2:$E$301,Livro_Diario!$D$2:$D$301,Balancete!$C8) -> 0 | F8: =D8-E8 -> 8298 | G8: =ABS(IF(F8>0,F8,0)) -> 8298 | H8: =ABS(IF(F8>0,0,F8)) -> 0
B9: ANC | C9: (-)Depreciação Acumulada | D9: =SUMIFS(Livro_Diario!$E$2:$E$301,Livro_Diario!$C$2:$C$301,Balancete!$C9) -> 0 | E9: =SUMIFS(Livro_Diario!$E$2:$E$301,Livro_Diario!$D$2:$D$301,Balancete!$C9) -> 596.4 | F9: =D9-E9 -> -596.4 | G9: =ABS(IF(F9>0,F9,0)) -> 0 | H9: =ABS(IF(F9>0,0,F9)) -> 596.4 | I9: cta redutora do ativo
B10: P | C10: Fornecedores | D10: =SUMIFS(Livro_Diario!$E$2:$E$301,Livro_Diario!$C$2:$C$301,Balancete!$C10) -> 0 | E10: =SUMIFS(Livro_Diario!$E$2:$E$301,Livro_Diario!$D$2:$D$301,Balancete!$C10) -> 0 | F10: =D10-E10 -> 0 | G10: =ABS(IF(F10>0,F10,0)) -> 0 | H10: =ABS(IF(F10>0,0,F10)) -> 0
B11: P | C11: Contas a Pagar | D11: =SUMIFS(Livro_Diario!$E$2:$E$301,Livro_Diario!$C$2:$C$301,Balancete!$C11) -> 2869.59 | E11: =SUMIFS(Livro_Diario!$E$2:$E$301,Livro_Diario!$D$2:$D$301,Balancete!$C11) -> 15558 | F11: =D11-E11 -> -12688.41 | G11: =ABS(IF(F11>0,F11,0)) -> 0 | H11: =ABS(IF(F11>0,0,F11)) -> 12688.41
B12: P | C12: Salários a Pagar | D12: =SUMIFS(Livro_Diario!$E$2:$E$301,Livro_Diario!$C$2:$C$301,Balancete!$C12) -> 4853.58 | E12: =SUMIFS(Livro_Diario!$E$2:$E$301,Livro_Diario!$D$2:$D$301,Balancete!$C12) -> 7336.4 | F12: =D12-E12 -> -2482.82 | G12: =ABS(IF(F12>0,F12,0)) -> 0 | H12: =ABS(IF(F12>0,0,F12)) -> 2482.82
B13: P | C13: VT a pagar | D13: =SUMIFS(Livro_Diario!$E$2:$E$301,Livro_Diario!$C$2:$C$301,Balancete!$C13) -> 0 | E13: =SUMIFS(Livro_Diario!$E$2:$E$301,Livro_Diario!$D$2:$D$301,Balancete!$C13) -> 440.18 | F13: =D13-E13 -> -440.18 | G13: =ABS(IF(F13>0,F13,0)) -> 0 | H13: =ABS(IF(F13>0,0,F13)) -> 440.18
B14: P | C14: 13º Sal. a pagar | D14: =SUMIFS(Livro_Diario!$E$2:$E$301,Livro_Diario!$C$2:$C$301,Balancete!$C14) -> 0 | E14: =SUMIFS(Livro_Diario!$E$2:$E$301,Livro_Diario!$D$2:$D$301,Balancete!$C14) -> 611.36 | F14: =D14-E14 -> -611.36 | G14: =ABS(IF(F14>0,F14,0)) -> 0 | H14: =ABS(IF(F14>0,0,F14)) -> 611.36
B15: P | C15: Férias a pagar | D15: =SUMIFS(Livro_Diario!$E$2:$E$301,Livro_Diario!$C$2:$C$301,Balancete!$C15) -> 0 | E15: =SUMIFS(Livro_Diario!$E$2:$E$301,Livro_Diario!$D$2:$D$301,Balancete!$C15) -> 815.12 | F15: =D15-E15 -> -815.12 | G15: =ABS(IF(F15>0,F15,0)) -> 0 | H15: =ABS(IF(F15>0,0,F15)) -> 815.12
B16: P | C16: FGTS a Recolher | D16: =SUMIFS(Livro_Diario!$E$2:$E$301,Livro_Diario!$C$2:$C$301,Balancete!$C16) -> 356.37 | E16: =SUMIFS(Livro_Diario!$E$2:$E$301,Livro_Diario!$D$2:$D$301,Balancete!$C16) -> 701.02 | F16: =D16-E16 -> -344.65 | G16: =ABS(IF(F16>0,F16,0)) -> 0 | H16: =ABS(IF(F16>0,0,F16)) -> 344.65
B17: P | C17: INSS a Recolher | D17: =SUMIFS(Livro_Diario!$E$2:$E$301,Livro_Diario!$C$2:$C$301,Balancete!$C17) -> 344.05 | E17: =SUMIFS(Livro_Diario!$E$2:$E$301,Livro_Diario!$D$2:$D$301,Balancete!$C17) -> 1890.14 | F17: =D17-E17 -> -1546.09 | G17: =ABS(IF(F17>0,F17,0)) -> 0 | H17: =ABS(IF(F17>0,0,F17)) -> 1546.09
B18: P | C18: ProLabore a Pagar | D18: =SUMIFS(Livro_Diario!$E$2:$E$301,Livro_Diario!$C$2:$C$301,Balancete!$C18) -> 8440 | E18: =SUMIFS(Livro_Diario!$E$2:$E$301,Livro_Diario!$D$2:$D$301,Balancete!$C18) -> 12000 | F18: =D18-E18 -> -3560 | G18: =ABS(IF(F18>0,F18,0)) -> 0 | H18: =ABS(IF(F18>0,0,F18)) -> 3560
B19: P | C19: IPTU a Pagar | D19: =SUMIFS(Livro_Diario!$E$2:$E$301,Livro_Diario!$C$2:$C$301,Balancete!$C19) -> 0 | E19: =SUMIFS(Livro_Diario!$E$2:$E$301,Livro_Diario!$D$2:$D$301,Balancete!$C19) -> 870 | F19: =D19-E19 -> -870 | G19: =ABS(IF(F19>0,F19,0)) -> 0 | H19: =ABS(IF(F19>0,0,F19)) -> 870
B20: P | C20: Provisões a Pagar | D20: =SUMIFS(Livro_Diario!$E$2:$E$301,Livro_Diario!$C$2:$C$301,Balancete!$C20) -> 0 | E20: =SUMIFS(Livro_Diario!$E$2:$E$301,Livro_Diario!$D$2:$D$301,Balancete!$C20) -> 0 | F20: =D20-E20 -> 0 | G20: =ABS(IF(F20>0,F20,0)) -> 0 | H20: =ABS(IF(F20>0,0,F20)) -> 0
B21: PL | C21: Capital Social Integralizado | D21: =SUMIFS(Livro_Diario!$E$2:$E$301,Livro_Diario!$C$2:$C$301,Balancete!$C21) -> 0 | E21: =SUMIFS(Livro_Diario!$E$2:$E$301,Livro_Diario!$D$2:$D$301,Balancete!$C21) -> 70000 | F21: =D21-E21 -> -70000 | G21: =ABS(IF(F21>0,F21,0)) -> 0 | H21: =ABS(IF(F21>0,0,F21)) -> 70000
... B24: Result. | C24: Honorários MEI | D24: =SUMIFS(Livro_Diario!$E$2:$E$301,Livro_Diario!$C$2:$C$301,Balancete!$C24) -> 0 | E24: =SUMIFS(Livro_Diario!$E$2:$E$301,Livro_Diario!$D$2:$D$301,Balancete!$C24) -> 3000 | F24: =D24-E24 -> -3000 | G24: =ABS(IF(F24>0,F24,0)) -> 0 | H24: =ABS(IF(F24>0,0,F24)) -> 3000
B25: Result. | C25: Receita com Consultoria Tributária | D25: =SUMIFS(Livro_Diario!$E$2:$E$301,Livro_Diario!$C$2:$C$301,Balancete!$C25) -> 0 | E25: =SUMIFS(Livro_Diario!$E$2:$E$301,Livro_Diario!$D$2:$D$301,Balancete!$C25) -> 2550 | F25: =D25-E25 -> -2550 | G25: =ABS(IF(F25>0,F25,0)) -> 0 | H25: =ABS(IF(F25>0,0,F25)) -> 2550 | I25: Total receitas
B26: Result. | C26: Receita com DIRPF (Simplificada) | D26: =SUMIFS(Livro_Diario!$E$2:$E$301,Livro_Diario!$C$2:$C$301,Balancete!$C26) -> 0 | E26: =SUMIFS(Livro_Diario!$E$2:$E$301,Livro_Diario!$D$2:$D$301,Balancete!$C26) -> 900 | F26: =D26-E26 -> -900 | G26: =ABS(IF(F26>0,F26,0)) -> 0 | H26: =ABS(IF(F26>0,0,F26)) -> 900 | I26: =H23+H24+H25+H26+H27+H28 -> 28120
B27: Result. | C27: Receita com DIRPF (Completa/Complexa) | D27: =SUMIFS(Livro_Diario!$E$2:$E$301,Livro_Diario!$C$2:$C$301,Balancete!$C27) -> 0 | E27: =SUMIFS(Livro_Diario!$E$2:$E$301,Livro_Diario!$D$2:$D$301,Balancete!$C27) -> 2200 | F27: =D27-E27 -> -2200 | G27: =ABS(IF(F27>0,F27,0)) -> 0 | H27: =ABS(IF(F27>0,0,F27)) -> 2200
B28: Result. | C28: Outros Serviços (DECORE / Abertura / DASN) | D28: =SUMIFS(Livro_Diario!$E$2:$E$301,Livro_Diario!$C$2:$C$301,Balancete!$C28) -> 0 | E28: =SUMIFS(Livro_Diario!$E$2:$E$301,Livro_Diario!$D$2:$D$301,Balancete!$C28) -> 10070 | F28: =D28-E28 -> -10070 | G28: =ABS(IF(F28>0,F28,0)) -> 0 | H28: =ABS(IF(F28>0,0,F28)) -> 10070
B29: Result. | C29: Custo com Tecnologia/TI | D29: =SUMIFS(Livro_Diario!$E$2:$E$301,Livro_Diario!$C$2:$C$301,Balancete!$C29) -> 590 | E29: =SUMIFS(Livro_Diario!$E$2:$E$301,Livro_Diario!$D$2:$D$301,Balancete!$C29) -> 0 | F29: =D29-E29 -> 590 | G29: =ABS(IF(F29>0,F29,0)) -> 590 | H29: =ABS(IF(F29>0,0,F29)) -> 0
B30: Result. | C30: Custo c/ ProLabore | D30: =SUMIFS(Livro_Diario!$E$2:$E$301,Livro_Diario!$C$2:$C$301,Balancete!$C30) -> 9000 | E30: =SUMIFS(Livro_Diario!$E$2:$E$301,Livro_Diario!$D$2:$D$301,Balancete!$C30) -> 0 | F30: =D30-E30 -> 9000 | G30: =ABS(IF(F30>0,F30,0)) -> 9000 | H30: =ABS(IF(F30>0,0,F30)) -> 0
B31: Result. | C31: Custo c/ Salários | D31: =SUMIFS(Livro_Diario!$E$2:$E$301,Livro_Diario!$C$2:$C$301,Balancete!$C31) -> 5236.4 | E31: =SUMIFS(Livro_Diario!$E$2:$E$301,Livro_Diario!$D$2:$D$301,Balancete!$C31) -> 0 | F31: =D31-E31 -> 5236.4 | G31: =ABS(IF(F31>0,F31,0)) -> 5236.4 | H31: =ABS(IF(F31>0,0,F31)) -> 0
B32: Result. | C32: Custo c/ INSS | D32: =SUMIFS(Livro_Diario!$E$2:$E$301,Livro_Diario!$C$2:$C$301,Balancete!$C32) -> 0 | E32: =SUMIFS(Livro_Diario!$E$2:$E$301,Livro_Diario!$D$2:$D$301,Balancete!$C32) -> 0 | F32: =D32-E32 -> 0 | G32: =ABS(IF(F32>0,F32,0)) -> 0 | H32: =ABS(IF(F32>0,0,F32)) -> 0
B33: Result. | C33: Custo c/ FGTS | D33: =SUMIFS(Livro_Diario!$E$2:$E$301,Livro_Diario!$C$2:$C$301,Balancete!$C33) -> 418.92 | E33: =SUMIFS(Livro_Diario!$E$2:$E$301,Livro_Diario!$D$2:$D$301,Balancete!$C33) -> 0 | F33: =D33-E33 -> 418.92 | G33: =ABS(IF(F33>0,F33,0)) -> 418.92 | H33: =ABS(IF(F33>0,0,F33)) -> 0
B34: Result. | C34: Custo c/ 13º Prov. | D34: =SUMIFS(Livro_Diario!$E$2:$E$301,Livro_Diario!$C$2:$C$301,Balancete!$C34) -> 436.37 | E34: =SUMIFS(Livro_Diario!$E$2:$E$301,Livro_Diario!$D$2:$D$301,Balancete!$C34) -> 0 | F34: =D34-E34 -> 436.37 | G34: =ABS(IF(F34>0,F34,0)) -> 436.37 | H34: =ABS(IF(F34>0,0,F34)) -> 0
B35: Result. | C35: Custo c/ Férias Prov. | D35: =SUMIFS(Livro_Diario!$E$2:$E$301,Livro_Diario!$C$2:$C$301,Balancete!$C35) -> 581.81 | E35: =SUMIFS(Livro_Diario!$E$2:$E$301,Livro_Diario!$D$2:$D$301,Balancete!$C35) -> 0 | F35: =D35-E35 -> 581.81 | G35: =ABS(IF(F35>0,F35,0)) -> 581.81 | H35: =ABS(IF(F35>0,0,F35)) -> 0
B36: Result. | C36: Custo c/ FGTS sobre Prov. | D36: =SUMIFS(Livro_Diario!$E$2:$E$301,Livro_Diario!$C$2:$C$301,Balancete!$C36) -> 81.46 | E36: =SUMIFS(Livro_Diario!$E$2:$E$301,Livro_Diario!$D$2:$D$301,Balancete!$C36) -> 0 | F36: =D36-E36 -> 81.46 | G36: =ABS(IF(F36>0,F36,0)) -> 81.46 | H36: =ABS(IF(F36>0,0,F36)) -> 0
B37: Result. | C37: Impostos Simples Nacional (DAS) | D37: =SUMIFS(Livro_Diario!$E$2:$E$301,Livro_Diario!$C$2:$C$301,Balancete!$C37) -> 1124.8 | E37: =SUMIFS(Livro_Diario!$E$2:$E$301,Livro_Diario!$D$2:$D$301,Balancete!$C37) -> 0 | F37: =D37-E37 -> 1124.8 | G37: =ABS(IF(F37>0,F37,0)) -> 1124.8 | H37: =ABS(IF(F37>0,0,F37)) -> 0
B38: Result. | C38: Despesa Água e Esgoto | D38: =SUMIFS(Livro_Diario!$E$2:$E$301,Livro_Diario!$C$2:$C$301,Balancete!$C38) -> 295.69 | E38: =SUMIFS(Livro_Diario!$E$2:$E$301,Livro_Diario!$D$2:$D$301,Balancete!$C38) -> 0 | F38: =D38-E38 -> 295.69 | G38: =ABS(IF(F38>0,F38,0)) -> 295.69 | H38: =ABS(IF(F38>0,0,F38)) -> 0
... B41: Result. | C41: Despesa Limpeza e Copa | D41: =SUMIFS(Livro_Diario!$E$2:$E$301,Livro_Diario!$C$2:$C$301,Balancete!$C41) -> 377.46 | E41: =SUMIFS(Livro_Diario!$E$2:$E$301,Livro_Diario!$D$2:$D$301,Balancete!$C41) -> 0 | F41: =D41-E41 -> 377.46 | G41: =ABS(IF(F41>0,F41,0)) -> 377.46 | H41: =ABS(IF(F41>0,0,F41)) -> 0
B42: Result. | C42: Desp. Taxas e Registros (JUCESP/Alvará/CRC) | D42: =SUMIFS(Livro_Diario!$E$2:$E$301,Livro_Diario!$C$2:$C$301,Balancete!$C42) -> 1907.42 | E42: =SUMIFS(Livro_Diario!$E$2:$E$301,Livro_Diario!$D$2:$D$301,Balancete!$C42) -> 0 | F42: =D42-E42 -> 1907.42 | G42: =ABS(IF(F42>0,F42,0)) -> 1907.42 | H42: =ABS(IF(F42>0,0,F42)) -> 0 | I42: total despesas | L42: Despesas + 8%
B43: Result. | C43: Despesas com Veículos (Combustível) | D43: =SUMIFS(Livro_Diario!$E$2:$E$301,Livro_Diario!$C$2:$C$301,Balancete!$C43) -> 730 | E43: =SUMIFS(Livro_Diario!$E$2:$E$301,Livro_Diario!$D$2:$D$301,Balancete!$C43) -> 0 | F43: =D43-E43 -> 730 | G43: =ABS(IF(F43>0,F43,0)) -> 730 | H43: =ABS(IF(F43>0,0,F43)) -> 0 | I43: =G38+G39+G40+G41+G42+G43+G44+G45+G46+G47+G49+G50+G51+G52+G53+G54+G55+G56+G58 -> 18852.9 | L43: 20361.25
B44: Result. | C44: Despesa Manutenção e Reformas no Imóvel | D44: =SUMIFS(Livro_Diario!$E$2:$E$301,Livro_Diario!$C$2:$C$301,Balancete!$C44) -> 2500 | E44: =SUMIFS(Livro_Diario!$E$2:$E$301,Livro_Diario!$D$2:$D$301,Balancete!$C44) -> 0 | F44: =D44-E44 -> 2500 | G44: =ABS(IF(F44>0,F44,0)) -> 2500 | H44: =ABS(IF(F44>0,0,F44)) -> 0
B45: Result. | C45: Despesa com Equipamento de Segurança | D45: =SUMIFS(Livro_Diario!$E$2:$E$301,Livro_Diario!$C$2:$C$301,Balancete!$C45) -> 288 | E45: =SUMIFS(Livro_Diario!$E$2:$E$301,Livro_Diario!$D$2:$D$301,Balancete!$C45) -> 0 | F45: =D45-E45 -> 288 | G45: =ABS(IF(F45>0,F45,0)) -> 288 | H45: =ABS(IF(F45>0,0,F45)) -> 0 | L45: =L43-I43 -> 1508.35 | N45: =1269+1508 -> 2777
B46: Result. | C46: Despesa com IPTU | D46: =SUMIFS(Livro_Diario!$E$2:$E$301,Livro_Diario!$C$2:$C$301,Balancete!$C46) -> 870 | E46: =SUMIFS(Livro_Diario!$E$2:$E$301,Livro_Diario!$D$2:$D$301,Balancete!$C46) -> 0 | F46: =D46-E46 -> 870 | G46: =ABS(IF(F46>0,F46,0)) -> 870 | H46: =ABS(IF(F46>0,0,F46)) -> 0
B47: Result. | C47: Despesa com Telefone e Internet | D47: =SUMIFS(Livro_Diario!$E$2:$E$301,Livro_Diario!$C$2:$C$301,Balancete!$C47) -> 279.96 | E47: =SUMIFS(Livro_Diario!$E$2:$E$301,Livro_Diario!$D$2:$D$301,Balancete!$C47) -> 0 | F47: =D47-E47 -> 279.96 | G47: =ABS(IF(F47>0,F47,0)) -> 279.96 | H47: =ABS(IF(F47>0,0,F47)) -> 0
B48: Result. | C48: Despesa com Tecnologia/TI | D48: =SUMIFS(Livro_Diario!$E$2:$E$301,Livro_Diario!$C$2:$C$301,Balancete!$C48) -> 0 | E48: =SUMIFS(Livro_Diario!$E$2:$E$301,Livro_Diario!$D$2:$D$301,Balancete!$C48) -> 0 | F48: =D48-E48 -> 0 | G48: =ABS(IF(F48>0,F48,0)) -> 0 | H48: =ABS(IF(F48>0,0,F48)) -> 0
B49: Result. | C49: Despesa com Publicidade/Redes Sociais | D49: =SUMIFS(Livro_Diario!$E$2:$E$301,Livro_Diario!$C$2:$C$301,Balancete!$C49) -> 2200 | E49: =SUMIFS(Livro_Diario!$E$2:$E$301,Livro_Diario!$D$2:$D$301,Balancete!$C49) -> 0 | F49: =D49-E49 -> 2200 | G49: =ABS(IF(F49>0,F49,0)) -> 2200 | H49: =ABS(IF(F49>0,0,F49)) -> 0
B50: Result. | C50: Despesa com Salários | D50: =SUMIFS(Livro_Diario!$E$2:$E$301,Livro_Diario!$C$2:$C$301,Balancete!$C50) -> 2100 | E50: =SUMIFS(Livro_Diario!$E$2:$E$301,Livro_Diario!$D$2:$D$301,Balancete!$C50) -> 0 | F50: =D50-E50 -> 2100 | G50: =ABS(IF(F50>0,F50,0)) -> 2100 | H50: =ABS(IF(F50>0,0,F50)) -> 0
B51: Result. | C51: Despesa c/ 13º Sal. | D51: =SUMIFS(Livro_Diario!$E$2:$E$301,Livro_Diario!$C$2:$C$301,Balancete!$C51) -> 174.99 | E51: =SUMIFS(Livro_Diario!$E$2:$E$301,Livro_Diario!$D$2:$D$301,Balancete!$C51) -> 0 | F51: =D51-E51 -> 174.99 | G51: =ABS(IF(F51>0,F51,0)) -> 174.99 | H51: =ABS(IF(F51>0,0,F51)) -> 0
B52: Result. | C52: Despesa c/ Férias | D52: =SUMIFS(Livro_Diario!$E$2:$E$301,Livro_Diario!$C$2:$C$301,Balancete!$C52) -> 233.31 | E52: =SUMIFS(Livro_Diario!$E$2:$E$301,Livro_Diario!$D$2:$D$301,Balancete!$C52) -> 0 | F52: =D52-E52 -> 233.31 | G52: =ABS(IF(F52>0,F52,0)) -> 233.31 | H52: =ABS(IF(F52>0,0,F52)) -> 0
B53: Result. | C53: Despesa c/ FGTS | D53: =SUMIFS(Livro_Diario!$E$2:$E$301,Livro_Diario!$C$2:$C$301,Balancete!$C53) -> 200.64 | E53: =SUMIFS(Livro_Diario!$E$2:$E$301,Livro_Diario!$D$2:$D$301,Balancete!$C53) -> 0 | F53: =D53-E53 -> 200.64 | G53: =ABS(IF(F53>0,F53,0)) -> 200.64 | H53: =ABS(IF(F53>0,0,F53)) -> 0
B54: Result. | C54: Despesa c/ Pró-labore | D54: =SUMIFS(Livro_Diario!$E$2:$E$301,Livro_Diario!$C$2:$C$301,Balancete!$C54) -> 3000 | E54: =SUMIFS(Livro_Diario!$E$2:$E$301,Livro_Diario!$D$2:$D$301,Balancete!$C54) -> 0 | F54: =D54-E54 -> 3000 | G54: =ABS(IF(F54>0,F54,0)) -> 3000 | H54: =ABS(IF(F54>0,0,F54)) -> 0
B55: Result. | C55: Despesa c/ VT | D55: =SUMIFS(Livro_Diario!$E$2:$E$301,Livro_Diario!$C$2:$C$301,Balancete!$C55) -> 910 | E55: =SUMIFS(Livro_Diario!$E$2:$E$301,Livro_Diario!$D$2:$D$301,Balancete!$C55) -> 0 | F55: =D55-E55 -> 910 | G55: =ABS(IF(F55>0,F55,0)) -> 910 | H55: =ABS(IF(F55>0,0,F55)) -> 0
B56: Result. | C56: Despesa c/ VR | D56: =SUMIFS(Livro_Diario!$E$2:$E$301,Livro_Diario!$C$2:$C$301,Balancete!$C56) -> 1204 | E56: =SUMIFS(Livro_Diario!$E$2:$E$301,Livro_Diario!$D$2:$D$301,Balancete!$C56) -> 0 | F56: =D56-E56 -> 1204 | G56: =ABS(IF(F56>0,F56,0)) -> 1204 | H56: =ABS(IF(F56>0,0,F56)) -> 0
B57: Result. | C57: Despesa c/ INSS | D57: =SUMIFS(Livro_Diario!$E$2:$E$301,Livro_Diario!$C$2:$C$301,Balancete!$C57) -> 0 | E57: =SUMIFS(Livro_Diario!$E$2:$E$301,Livro_Diario!$D$2:$D$301,Balancete!$C57) -> 0 | F57: =D57-E57 -> 0 | G57: =ABS(IF(F57>0,F57,0)) -> 0 | H57: =ABS(IF(F57>0,0,F57)) -> 0
... B59: Result. | C59: Depreciação do Período | D59: =SUMIFS(Livro_Diario!$E$2:$E$301,Livro_Diario!$C$2:$C$301,Balancete!$C59) -> 0 | E59: =SUMIFS(Livro_Diario!$E$2:$E$301,Livro_Diario!$D$2:$D$301,Balancete!$C59) -> 0 | F59: =D59-E59 -> 0 | G59: =ABS(IF(F59>0,F59,0)) -> 0 | H59: =ABS(IF(F59>0,0,F59)) -> 0
B60: Total | D60: =SUM(D4:D59) -> 166864.25 | E60: =SUM(E4:E59) -> 166864.25 | F60: =SUM(F4:F59) -> 5.9117156e-12 | G60: =SUM(G4:G59) -> 122075.03 | H60: =SUM(H4:H59) -> 122075.03

Sheet Cópia_Balancete
B1: Balancete de Verificação - 1º Trimestre/2025
B2: Grupo | C2: Conta | D2: Débito | E2: Crédito
B3: A | C3: Caixa/Banco | D3: 70194.37 | E3: 0
B4: A | C4: Honorários a Receber | D4: 0 | E4: 0
B5: ANC | C5: Imóveis (Sede Própria) | D5: 0 | E5: 0
B6: ANC | C6: Móveis e Utensílios | D6: 7260 | E6: 0
B7: ANC | C7: Computadores e Periféricos | D7: 8298 | E7: 0
B8: ANC | C8: (-)Depreciação Acumulada | D8: 0 | E8: 596.4
B9: P | C9: Contas a Pagar | D9: 0 | E9: 12688.41
B10: P | C10: Salários a Pagar | D10: 0 | E10: 2482.82
B11: P | C11: VT a pagar | D11: 0 | E11: 440.18
B12: P | C12: 13º Sal. a pagar | D12: 0 | E12: 611.36
B13: P | C13: Férias a pagar | D13: 0 | E13: 815.12
B14: P | C14: FGTS a Recolher | D14: 0 | E14: 344.65
... B56: Result. | C56: Despesa c/ depreciação | D56: 596.4 | E56: 0
B57: Total | D57: =SUM(D3:D56) -> 122075.03 | E57: =SUM(E3:E56) -> 122075.03

Sheet Folha_Pagamento
A2: 1º Trimestre
B4: adm. 09/01/2025 | E4: adm. 20/01/2025
B5: 2X por semana - 4h/dia | E5: 200h/mês - 40h semanais
B6: Auxiliar de Serviços Gerais | E6: Assistente Administrativo | H6: Folha Mês de Janeiro
B8: Salário Bruto | C8: 700 | E8: Salário Bruto | F8: 872.76 | H8: Salário Bruto | I8: =C8+F8 -> 1572.76 | K8: calcular desconto do INSS
B9: INSS 7,5% | C9: 52.5 | E9: INSS 9% | F9: 65.46 | H9: INSS | I9: =C9+F9 -> 117.96
B10: VT | C10: 42 | E10: VT | F10: 52.36 | H10: VT | I10: =C10+F10 -> 94.36
B11: Vr. Líquido | C11: =700-C9-C10 -> 605.5 | E11: Vr. Líquido | F11: =F8-F9-F10 -> 754.94 | H11: Vr. Líquido | I11: =I8-I9-I10 -> 1360.44
B12: FGTS 8% | C12: 56 | E12: FGTS 8% | F12: 69.82 | H12: FGTS 8% | I12: =C12+F12 -> 125.82
B13: Prov Férias + 1/3 | C13: 77.77 | E13: Prov Férias + 1/3 | F13: 96.97 | H13: Prov Férias + 1/3 | I13: =C13+F13 -> 174.74
B14: Prov 13º Salário | C14: 58.33 | E14: Prov 13º Salário | F14: 72.73 | H14: Prov 13º Salário | I14: =C14+F14 -> 131.06
B15: FGTS sobre Provisões | C15: 10.88 | E15: FGTS sobre Provisões | F15: 13.58 | H15: FGTS sobre Provisões | I15: =C15+F15 -> 24.46
B16: VT Empresa | C16: 91 | D16: 7 dias | E16: VT Empresa | F16: 130 | G16: 10 dias | H16: VT Empresa | I16: =C16+F16 -> 221
B17: Vale Refeição | C17: 150 | E17: Vale Refeição | F17: 174 | H17: Vale Refeição | I17: =C17+F17 -> 324
A18: Total: | C18: =C11+C12+C13+C14+C15+C16+C17 -> 1049.48 | F18: =F11+F12+F13+F14+F15+F16+F17 -> 1312.04 | I18: =I11+I12+I13+I14+I15+I16+I17 -> 2361.52
B20: Auxiliar de Serviços Gerais | E20: Assistente Administrativo | H20: Folha Mês de Fevereiro
B22: Salário Bruto | C22: 700 | E22: Salário Bruto | F22: 2181.82 | H22: Salário Bruto | I22: =C22+F22 -> 2881.82
B23: INSS 7,5% | C23: 52.5 | E23: INSS 9% | F23: 173.59 | H23: INSS | I23: =C23+F23 -> 226.09
B24: Vale TRansporte | C24: 42 | E24: VT | F24: 130.91 | H24: VT | I24: =C24+F24 -> 172.91
B25: Valor Líquido | C25: =C22-C23-C24 -> 605.5 | E25: Valor Líquido | F25: =F22-F23-F24 -> 1877.32 | H25: Vr. Líquido | I25: =I22-I23-I24 -> 2482.82
B26: FGTS 8% | C26: 56 | E26: FGTS 8% | F26: 174.55 | H26: FGTS 8% | I26: =C26+F26 -> 230.55
B27: Prov Férias + 1/3 | C27: 77.77 | E27: Prov Férias + 1/3 | F27: 242.42 | H27: Prov Férias + 1/3 | I27: =C27+F27 -> 320.19
B28: Prov 13º Salário | C28: 58.33 | E28: Prov 13º Salário | F28: 181.82 | H28: Prov 13º Salário | I28: =C28+F28 -> 240.15
B29: FGTS sobre Provisões | C29: 10.88 | E29: FGTS sobre Provisões | F29: 33.94 | H29: FGTS sobre Provisões | I29: =C29+F29 -> 44.82
B30: VT Empresa | C30: 104 | D30: 8 dias | E30: VT Empresa | F30: 260 | G30: 20 dias | H30: VT Empresa | I30: =C30+F30 -> 364
B31: Vale Refeição | C31: 150 | E31: Vale Refeição | F31: 290 | H31: Vale Refeição | I31: =C31+F31 -> 440
A32: Total: | C32: =C25+C26+C27+C28+C29+C30+C31 -> 1062.48 | F32: =F25+F26+F27+F28+F29+F30+F31 -> 3060.05 | I32: =I25+I26+I27+I28+I29+I30+I31 -> 4122.53
B34: Auxiliar de Serviços Gerais | E34: Assistente Administrativo | H34: Folha Mês de Março
B36: Salário Bruto | C36: 700 | E36: Salário Bruto | F36: 2181.82 | H36: Salário Bruto | I36: =C36+F36 -> 2881.82
B37: INSS 7,5% | C37: 52.5 | E37: INSS 9% | F37: 173.59 | H37: INSS | I37: =C37+F37 -> 226.09
B38: Vale TRansporte | C38: 42 | E38: VT | F38: 130.91 | H38: VT | I38: =C38+F38 -> 172.91
B39: Valor Líquido | C39: =C36-C37-C38 -> 605.5 | E39: Valor Líquido | F39: =F36-F37-F38 -> 1877.32 | H39: Vr. Líquido | I39: =I36-I37-I38 -> 2482.82
B40: FGTS 8% | C40: 56 | E40: FGTS 8% | F40: 174.55 | H40: FGTS 8% | I40: =C40+F40 -> 230.55
B41: Prov Férias + 1/3 | C41: 77.77 | E41: Prov Férias + 1/3 | F41: 242.42 | H41: Prov Férias + 1/3 | I41: =C41+F41 -> 320.19
B42: Prov 13º Salário | C42: 58.33 | E42: Prov 13º Salário | F42: 181.82 | H42: Prov 13º Salário | I42: =C42+F42 -> 240.15
B43: FGTS sobre Provisões | C43: 10.88 | E43: FGTS sobre Provisões | F43: 33.94 | H43: FGTS sobre Provisões | I43: =C43+F43 -> 44.82
B44: VT Empresa | C44: 91 | D44: 7 dias | E44: VT Empresa | F44: 234 | G44: 18 dias | H44: VT Empresa | I44: =C44+F44 -> 325
B45: Vale Refeição | C45: 150 | E45: Vale Refeição | F45: 290 | H45: Vale Refeição | I45: =C45+F45 -> 440
A46: Total: | C46: =C39+C40+C41+C42+C43+C44+C45 -> 1049.48 | F46: =F39+F40+F41+F42+F43+F44+F45 -> 3034.05 | I46: =I39+I40+I41+I42+I43+I44+I45 -> 4083.53
A48: Custo Total 1º Trimestre: | C48: =C18+C46+C32 -> 3161.44 | F48: =F18+F32+F46 -> 7406.14 | I48: =I18+I32+I46 -> 10567.58
A50: 2º Trimestre
B52: Auxiliar de Serviços Gerais | E52: Assistente Administrativo | H52: Folha Mês de Abril
B54: Salário Bruto | C54: 700 | E54: Salário Bruto | F54: 2181.82 | H54: Salário Bruto | I54: =C54+F54 -> 2881.82
B55: INSS 7,5% | C55: 52.5 | E55: INSS 9% | F55: 173.59 | H55: INSS | I55: =C55+F55 -> 226.09
B56: Vale TRansporte | C56: 42 | E56: VT | F56: 130.91 | H56: VT | I56: =C56+F56 -> 172.91
B57: Valor Líquido | C57: =C54-C55-C56 -> 605.5 | E57: Valor Líquido | F57: =F54-F55-F56 -> 1877.32 | H57: Vr. Líquido | I57: =I54-I55-I56 -> 2482.82
B58: FGTS 8% | C58: 56 | E58: FGTS 8% | F58: 174.55 | H58: FGTS 8% | I58: =C58+F58 -> 230.55
B59: Prov Férias + 1/3 | C59: 77.77 | E59: Prov Férias + 1/3 | F59: 242.42 | H59: Prov Férias + 1/3 | I59: =C59+F59 -> 320.19
B60: Prov 13º Salário | C60: 58.33 | E60: Prov 13º Salário | F60: 181.82 | H60: Prov 13º Salário | I60: =C60+F60 -> 240.15
B61: FGTS sobre Provisões | C61: 10.88 | E61: FGTS sobre Provisões | F61: 33.94 | H61: FGTS sobre Provisões | I61: =C61+F61 -> 44.82
B62: VT Empresa | C62: 117 | D62: 9 dias | E62: VT Empresa | F62: 260 | G62: 20 dias | H62: VT Empresa | I62: =C62+F62 -> 377
B63: Vale Refeição | C63: 150 | E63: Vale Refeição | F63: 290 | H63: Vale Refeição | I63: =C63+F63 -> 440
A64: Total: | C64: =C57+C58+C59+C60+C61+C62+C63 -> 1075.48 | F64: =F57+F58+F59+F60+F61+F62+F63 -> 3060.05 | I64: =I57+I58+I59+I60+I61+I62+I63 -> 4135.53
B66: Auxiliar de Serviços Gerais | E66: Assistente Administrativo | H66: Folha Mês de Maio
B68: Salário Bruto | C68: 700 | E68: Salário Bruto | F68: 2181.82 | H68: Salário Bruto | I68: =C68+F68 -> 2881.82
B69: INSS 7,5% | C69: 52.5 | E69: INSS 9% | F69: 173.59 | H69: INSS | I69: =C69+F69 -> 226.09
B70: Vale TRansporte | C70: 42 | E70: VT | F70: 130.91 | H70: VT | I70: =C70+F70 -> 172.91
B71: Valor Líquido | C71: =C68-C69-C70 -> 605.5 | E71: Valor Líquido | F71: =F68-F69-F70 -> 1877.32 | H71: Vr. Líquido | I71: =I68-I69-I70 -> 2482.82
B72: FGTS 8% | C72: 56 | E72: FGTS 8% | F72: 174.55 | H72: FGTS 8% | I72: =C72+F72 -> 230.55
B73: Prov Férias + 1/3 | C73: 77.77 | E73: Prov Férias + 1/3 | F73: 242.42 | H73: Prov Férias + 1/3 | I73: =C73+F73 -> 320.19
B74: Prov 13º Salário | C74: 58.33 | E74: Prov 13º Salário | F74: 181.82 | H74: Prov 13º Salário | I74: =C74+F74 -> 240.15
B75: FGTS sobre Provisões | C75: 10.88 | E75: FGTS sobre Provisões | F75: 33.94 | H75: FGTS sobre Provisões | I75: =C75+F75 -> 44.82
B76: VT Empresa | C76: 104 | D76: 8 dias | E76: VT Empresa | F76: 260 | G76: 20 dias | H76: VT Empresa | I76: =C76+F76 -> 364
B77: Vale Refeição | C77: 150 | E77: Vale Refeição | F77: 290 | H77: Vale Refeição | I77: =C77+F77 -> 440
A78: Total: | C78: =C71+C72+C73+C74+C75+C76+C77 -> 1062.48 | F78: =F71+F72+F73+F74+F75+F76+F77 -> 3060.05 | I78: =I71+I72+I73+I74+I75+I76+I77 -> 4122.53
B80: Auxiliar de Serviços Gerais | E80: Assistente Administrativo | H80: Folha Mês de Junho
B82: Salário Bruto | C82: 700 | E82: Salário Bruto | F82: 2181.82 | H82: Salário Bruto | I82: =C82+F82 -> 2881.82
B83: INSS 7,5% | C83: 52.5 | E83: INSS 9% | F83: 173.59 | H83: INSS | I83: =C83+F83 -> 226.09
B84: Vale TRansporte | C84: 42 | E84: VT | F84: 130.91 | H84: VT | I84: =C84+F84 -> 172.91
B85: Valor Líquido | C85: =C82-C83-C84 -> 605.5 | E85: Valor Líquido | F85: =F82-F83-F84 -> 1877.32 | H85: Vr. Líquido | I85: =I82-I83-I84 -> 2482.82
B86: FGTS 8% | C86: 56 | E86: FGTS 8% | F86: 174.55 | H86: FGTS 8% | I86: =C86+F86 -> 230.55
B87: Prov Férias + 1/3 | C87: 77.77 | E87: Prov Férias + 1/3 | F87: 242.42 | H87: Prov Férias + 1/3 | I87: =C87+F87 -> 320.19
B88: Prov 13º Salário | C88: 58.33 | E88: Prov 13º Salário | F88: 181.82 | H88: Prov 13º Salário | I88: =C88+F88 -> 240.15
B89: FGTS sobre Provisões | C89: 10.88 | E89: FGTS sobre Provisões | F89: 33.94 | H89: FGTS sobre Provisões | I89: =C89+F89 -> 44.82
B90: VT Empresa | C90: 91 | D90: 7 dias | E90: VT Empresa | F90: 247 | G90: 19 dias | H90: VT Empresa | I90: =C90+F90 -> 338
B91: Vale Refeição | C91: 150 | E91: Vale Refeição | F91: 290 | H91: Vale Refeição | I91: =C91+F91 -> 440
A92: Total: | C92: =C85+C86+C87+C88+C89+C90+C91 -> 1049.48 | F92: =F85+F86+F87+F88+F89+F90+F91 -> 3047.05 | I92: =I85+I86+I87+I88+I89+I90+I91 -> 4096.53
A94: Custo Total 2º Trimestre: | C94: =C64+C92+C78 -> 3187.44 | F94: =F64+F78+F92 -> 9167.15 | I94: =I64+I78+I92 -> 12354.59
C97: Pró-Labore | D97: Valor | E97: Coluna1
C98: Sócio 1 | D98: 3000 | E98: custo
C99: INSS 11% | D99: 330 | E99: encago do sócio
C100: Valor Líq. | D100: =D98-D99 -> 2670 | E100: liquido que vai sair do caixa
C101: Sócio 2 | D101: 1000
C102: INSS 11% | D102: 110
C103: Valor Líq. | D103: =D101-D102 -> 890
C104: Total | D104: =D98+D99+D101+D102 -> 4440
C113: Pró-Labore | D113: Valor
C114: Contador | D114: 3000
C115: INSS 11% | D115: 330
C116: Valor Líq. | D116: =D114-D115 -> 2670
